LICENSE
README.md
setup.py
pput/__init__.py
pput/main.py
pput.egg-info/PKG-INFO
pput.egg-info/SOURCES.txt
pput.egg-info/dependency_links.txt
pput.egg-info/entry_points.txt
pput.egg-info/requires.txt
pput.egg-info/top_level.txt